PdfandEmail.py
PdfandEmail-0.0.1.dist-info/METADATA
PdfandEmail-0.0.1.dist-info/WHEEL
PdfandEmail-0.0.1.dist-info/top_level.txt
PdfandEmail-0.0.1.dist-info/RECORD
