Metadata-Version: 2.1
Name: PdfandEmail
Version: 0.0.1
Summary: Any format to pdf converter and Attach PDF in email
Home-page: UNKNOWN
Author: Apekshya Rimal
License: UNKNOWN
Platform: UNKNOWN
Classifier: Programming Language :: Python :: 3.0
Classifier: Programming Language :: Python :: 3.7
Classifier: Programming Language :: Python :: 3.8
